MLExpRecords/__init__.py
MLExpRecords/entry.py
MLExpRecords/experiment.py
MLExpRecords/round.py
MLExpRecords/stage.py
MLExpRecords/storage.py
mlexprecords-0.0.1.dist-info/licenses/LICENSE
mlexprecords-0.0.1.dist-info/METADATA
mlexprecords-0.0.1.dist-info/WHEEL
mlexprecords-0.0.1.dist-info/top_level.txt
mlexprecords-0.0.1.dist-info/RECORD
