Metadata-Version: 2.4
Name: mlexprecords
Version: 0.0.1
Summary: 深度学习实验记录工具
Requires-Python: >=3
License-File: LICENSE
Requires-Dist: loguru
Requires-Dist: psutil
Requires-Dist: pyyaml
Dynamic: license-file
